oct4th/__init__.py
oct4th/main.py
oct4th-1.0.1.data/scripts/main.py
oct4th-1.0.1.dist-info/METADATA
oct4th-1.0.1.dist-info/WHEEL
oct4th-1.0.1.dist-info/entry_points.txt
oct4th-1.0.1.dist-info/top_level.txt
oct4th-1.0.1.dist-info/RECORD
