Metadata-Version: 2.1
Name: oct4th
Version: 1.0.1
Summary: Convert CSV/TSV files into XLSX
Home-page: https://github.com/robertaboukhalil/oct4th
Author: Robert Aboukhalil
Author-email: robert.aboukhalil@gmail.com
License: UNKNOWN
Platform: UNKNOWN
Classifier: Programming Language :: Python :: 3
Classifier: License :: OSI Approved :: MIT License
Classifier: Operating System :: OS Independent
Requires-Python: >=3.6
Requires-Dist: setuptools
Requires-Dist: xlsxwriter
